talbotextractor/__init__.py
talbotextractor/data/mask.fits
talbotextractor/data/test.fits
talbotextractor/exposure.py
talbotextractor/extractor.py
talbotextractor/frame.py
talbotextractor/utils.py
talbotextractor-0.2.2.dist-info/METADATA
talbotextractor-0.2.2.dist-info/WHEEL
talbotextractor-0.2.2.dist-info/licenses/LICENSE
talbotextractor-0.2.2.dist-info/RECORD
