Metadata-Version: 2.4
Name: talbotextractor
Version: 0.2.2
Summary: 
License-File: LICENSE
Author: Christina Hedges
Author-email: christina.l.hedges@nasa.gov
Requires-Python: >=3.9,<4.0
Classifier: Programming Language :: Python :: 3
Classifier: Programming Language :: Python :: 3.9
Classifier: Programming Language :: Python :: 3.10
Classifier: Programming Language :: Python :: 3.11
Classifier: Programming Language :: Python :: 3.12
Classifier: Programming Language :: Python :: 3.13
Classifier: Programming Language :: Python :: 3.14
Requires-Dist: appdirs (>=1.4.4,<2.0.0)
Requires-Dist: astropy (>=6.0.0)
Requires-Dist: corner (>=2.2.3,<3.0.0)
Requires-Dist: fitsio (>=1.2.6,<2.0.0)
Requires-Dist: lamatrix (>=1.0.1,<2.0.0)
Requires-Dist: matplotlib (>=3.0.0)
Requires-Dist: numpy (>=1.2)
Requires-Dist: pandas (>=2.2.3,<3.0.0)
Requires-Dist: rich (>=13.9.4,<14.0.0)
Requires-Dist: sparse3d (>=1.2.10)
Requires-Dist: tqdm (>=4.67.1,<5.0.0)
